CHANGES.txt
INSTALL.txt
LICENSE.txt
MANIFEST.in
README.txt
setup.py
urlminer/__init__.py
urlminer/urlminer.py
urlminer.egg-info/PKG-INFO
urlminer.egg-info/SOURCES.txt
urlminer.egg-info/dependency_links.txt
urlminer.egg-info/top_level.txt